README.txt
setup.cfg
setup.py
docs/HISTORY.txt
docs/INSTALL.txt
docs/LICENSE.GPL
docs/LICENSE.txt
my315ok/__init__.py
my315ok.portlet.logo.egg-info/PKG-INFO
my315ok.portlet.logo.egg-info/SOURCES.txt
my315ok.portlet.logo.egg-info/dependency_links.txt
my315ok.portlet.logo.egg-info/entry_points.txt
my315ok.portlet.logo.egg-info/namespace_packages.txt
my315ok.portlet.logo.egg-info/not-zip-safe
my315ok.portlet.logo.egg-info/paster_plugins.txt
my315ok.portlet.logo.egg-info/requires.txt
my315ok.portlet.logo.egg-info/top_level.txt
my315ok/portlet/__init__.py
my315ok/portlet/logo/__init__.py
my315ok/portlet/logo/configure.zcml
my315ok/portlet/logo/image.py
my315ok/portlet/logo/imageview.py
my315ok/portlet/logo/inputwidget.pt
my315ok/portlet/logo/interfaces.py
my315ok/portlet/logo/logoportlet.pt
my315ok/portlet/logo/logoportlet.py
my315ok/portlet/logo/version.txt
my315ok/portlet/logo/widget.py
my315ok/portlet/logo/js/DD_belatedPNG.js
my315ok/portlet/logo/locales/my315ok.portlet.logo.pot
my315ok/portlet/logo/locales/zh/LC_MESSAGES/my315ok.portlet.logo.mo
my315ok/portlet/logo/locales/zh/LC_MESSAGES/my315ok.portlet.logo.po
my315ok/portlet/logo/profiles/default/jsregistry.xml
my315ok/portlet/logo/profiles/default/metadata.xml
my315ok/portlet/logo/profiles/default/portlets.xml
my315ok/portlet/logo/tests/__init__.py
my315ok/portlet/logo/tests/base.py
my315ok/portlet/logo/tests/test_portlet.py