Metadata-Version: 1.0
Name: my315ok.portlet.logo
Version: 1.0dev-r191
Summary: a portlet for customize site logo
Home-page: http://315ok.org
Author: adam tang
Author-email: yuejun.tang@gmail.com
License: GPL
Keywords: logo portlet
Platform: UNKNOWN
Classifier: Framework :: Plone
Classifier: Programming Language :: Python
Classifier: Topic :: Software Development :: Libraries :: Python Modules
